{
  "model": "lamborghini-huracan",
  "points": [
    {
      "date": "2026-05-24",
      "overall": {
        "avg_price": 294085,
        "median_price": 282994,
        "count": 234
      },
      "by_variant": {
        "LP610-4": 243548,
        "Spyder": 248476,
        "Performante": 355070,
        "EVO": 295035,
        "STO": 423250,
        "Tecnica": 343950
      }
    },
    {
      "date": "2026-05-25",
      "overall": {
        "avg_price": 294587,
        "median_price": 286521,
        "count": 234
      },
      "by_variant": {
        "LP610-4": 245824,
        "Spyder": 248476,
        "Performante": 352407,
        "EVO": 297418,
        "STO": 423150,
        "Tecnica": 340643
      }
    },
    {
      "date": "2026-05-26",
      "overall": {
        "avg_price": 295355,
        "median_price": 285820,
        "count": 235
      },
      "by_variant": {
        "LP610-4": 245903,
        "Spyder": 252139,
        "Performante": 352407,
        "EVO": 297066,
        "STO": 423285,
        "Tecnica": 340775
      }
    },
    {
      "date": "2026-05-27",
      "overall": {
        "avg_price": 294492,
        "median_price": 282000,
        "count": 235
      },
      "by_variant": {
        "LP610-4": 246729,
        "Spyder": 244119,
        "Performante": 354401,
        "EVO": 293816,
        "STO": 423285,
        "Tecnica": 340643
      }
    },
    {
      "date": "2026-05-28",
      "overall": {
        "avg_price": 295177,
        "median_price": 285820,
        "count": 235
      },
      "by_variant": {
        "LP610-4": 247493,
        "Spyder": 242140,
        "Performante": 354401,
        "EVO": 295365,
        "STO": 423047,
        "Tecnica": 340443
      }
    },
    {
      "date": "2026-05-29",
      "overall": {
        "avg_price": 292584,
        "median_price": 279997,
        "count": 252
      },
      "by_variant": {
        "LP610-4": 247361,
        "Spyder": 241036,
        "Performante": 349965,
        "EVO": 295342,
        "STO": 428438,
        "Tecnica": 341079
      }
    },
    {
      "date": "2026-05-30",
      "overall": {
        "avg_price": 293369,
        "median_price": 279999,
        "count": 237
      },
      "by_variant": {
        "LP610-4": 248060,
        "Spyder": 241036,
        "Performante": 354004,
        "EVO": 297370,
        "STO": 431333,
        "Tecnica": 340584
      }
    },
    {
      "date": "2026-05-31",
      "overall": {
        "avg_price": 293295,
        "median_price": 282000,
        "count": 239
      },
      "by_variant": {
        "LP610-4": 248682,
        "Spyder": 233431,
        "Performante": 354988,
        "EVO": 298508,
        "STO": 425492,
        "Tecnica": 344203
      }
    },
    {
      "date": "2026-06-01",
      "overall": {
        "avg_price": 296222,
        "median_price": 284388,
        "count": 242
      },
      "by_variant": {
        "LP610-4": 247556,
        "Spyder": 233431,
        "Performante": 346538,
        "EVO": 301658,
        "STO": 433041,
        "Tecnica": 342583
      }
    },
    {
      "date": "2026-06-02",
      "overall": {
        "avg_price": 296042,
        "median_price": 281994,
        "count": 240
      },
      "by_variant": {
        "LP610-4": 249529,
        "Spyder": 233431,
        "Performante": 344642,
        "EVO": 302033,
        "STO": 434746,
        "Tecnica": 342531
      }
    },
    {
      "date": "2026-06-03",
      "overall": {
        "avg_price": 294567,
        "median_price": 284388,
        "count": 236
      },
      "by_variant": {
        "LP610-4": 251245,
        "Spyder": 233488,
        "Performante": 340064,
        "EVO": 301728,
        "STO": 434476,
        "Tecnica": 342400
      }
    },
    {
      "date": "2026-06-04",
      "overall": {
        "avg_price": 297107,
        "median_price": 285409,
        "count": 242
      },
      "by_variant": {
        "LP610-4": 251465,
        "Spyder": 234201,
        "Performante": 342000,
        "EVO": 301922,
        "STO": 426415,
        "Tecnica": 342714
      }
    },
    {
      "date": "2026-06-05",
      "overall": {
        "avg_price": 297054,
        "median_price": 284789,
        "count": 241
      },
      "by_variant": {
        "LP610-4": 249159,
        "Spyder": 224923,
        "Performante": 348152,
        "EVO": 300437,
        "STO": 425673,
        "Tecnica": 342615
      }
    },
    {
      "date": "2026-06-06",
      "overall": {
        "avg_price": 296017,
        "median_price": 284472,
        "count": 109
      },
      "by_variant": {
        "LP610-4": 266413,
        "Spyder": 223051,
        "Performante": 367482,
        "EVO": 294511,
        "STO": 421150,
        "Tecnica": 341260
      }
    },
    {
      "date": "2026-06-07",
      "overall": {
        "avg_price": 297755,
        "median_price": 288400,
        "count": 232
      },
      "by_variant": {
        "LP610-4": 251680,
        "Spyder": 225631,
        "Performante": 358601,
        "EVO": 303523,
        "STO": 421357,
        "Tecnica": 343288
      }
    },
    {
      "date": "2026-06-08",
      "overall": {
        "avg_price": 297459,
        "median_price": 288500,
        "count": 230
      },
      "by_variant": {
        "LP610-4": 252564,
        "Spyder": 225631,
        "Performante": 358601,
        "EVO": 303131,
        "STO": 416774,
        "Tecnica": 340695
      }
    },
    {
      "date": "2026-06-09",
      "overall": {
        "avg_price": 299400,
        "median_price": 289996,
        "count": 228
      },
      "by_variant": {
        "LP610-4": 251644,
        "Spyder": 219570,
        "Performante": 358601,
        "EVO": 304453,
        "STO": 415479,
        "Tecnica": 343169
      }
    },
    {
      "date": "2026-06-10",
      "overall": {
        "avg_price": 298220,
        "median_price": 289450,
        "count": 232
      },
      "by_variant": {
        "LP610-4": 252212,
        "Spyder": 218184,
        "Performante": 358518,
        "EVO": 301476,
        "STO": 418712,
        "Tecnica": 342566
      }
    },
    {
      "date": "2026-06-11",
      "overall": {
        "avg_price": 297402,
        "median_price": 285209,
        "count": 232
      },
      "by_variant": {
        "LP610-4": 246733,
        "Spyder": 225319,
        "Performante": 359593,
        "EVO": 305721,
        "STO": 418948,
        "Tecnica": 342232
      }
    },
    {
      "date": "2026-06-12",
      "overall": {
        "avg_price": 297186,
        "median_price": 285420,
        "count": 225
      },
      "by_variant": {
        "LP610-4": 245075,
        "Spyder": 234688,
        "Performante": 360979,
        "EVO": 305371,
        "STO": 418523,
        "Tecnica": 342232
      }
    },
    {
      "date": "2026-06-13",
      "overall": {
        "avg_price": 296233,
        "median_price": 289000,
        "count": 227
      },
      "by_variant": {
        "LP610-4": 246744,
        "Spyder": 223070,
        "Performante": 363300,
        "EVO": 308675,
        "STO": 415653,
        "Tecnica": 343914
      }
    },
    {
      "date": "2026-06-14",
      "overall": {
        "avg_price": 299463,
        "median_price": 289450,
        "count": 226
      },
      "by_variant": {
        "LP610-4": 248685,
        "Spyder": 223070,
        "Performante": 361711,
        "EVO": 303014,
        "STO": 423748,
        "Tecnica": 339628
      }
    },
    {
      "date": "2026-06-15",
      "overall": {
        "avg_price": 301139,
        "median_price": 290443,
        "count": 226
      },
      "by_variant": {
        "LP610-4": 250374,
        "Spyder": 223070,
        "Performante": 359661,
        "EVO": 306450,
        "STO": 423898,
        "Tecnica": 342711
      }
    },
    {
      "date": "2026-06-16",
      "overall": {
        "avg_price": 299966,
        "median_price": 289996,
        "count": 227
      },
      "by_variant": {
        "LP610-4": 249309,
        "Spyder": 234688,
        "Performante": 359661,
        "EVO": 304538,
        "STO": 423748,
        "Tecnica": 339874
      }
    },
    {
      "date": "2026-06-17",
      "overall": {
        "avg_price": 299210,
        "median_price": 289988,
        "count": 227
      },
      "by_variant": {
        "LP610-4": 248198,
        "Spyder": 226136,
        "Performante": 359661,
        "EVO": 304538,
        "STO": 423748,
        "Tecnica": 339874
      }
    }
  ]
}
